{
  "operationId": "atlassianGetcreateissuemetaissuetypeid",
  "method": "GET",
  "path": "/rest/api/3/issue/createmeta/{projectIdOrKey}/issuetypes/{issueTypeId}",
  "summary": "Atlassian Get Create Field Metadata For A Project And Issue Type Id",
  "requestExamples": [],
  "responseExamples": [
    {
      "status": "200",
      "contentType": "application/json",
      "example": "{\"fields\":[{\"fieldId\":\"assignee\",\"hasDefaultValue\":false,\"key\":\"assignee\",\"name\":\"Assignee\",\"operations\":[\"set\"],\"required\":true}],\"maxResults\":1,\"startAt\":0,\"total\":1}"
    },
    {
      "status": "400",
      "contentType": "application/json",
      "example": "{\"errorMessages\":[\"Parameter 'maxResults' must not exceed the limit '200'\"],\"errors\":{},\"httpStatusCode\":{\"empty\":false,\"present\":true}}"
    }
  ]
}