{
  "operationId": "atlassianGetissuetypeschemeforprojects",
  "method": "GET",
  "path": "/rest/api/3/issuetypescheme/project",
  "summary": "Atlassian Get Issue Type Schemes For Projects",
  "requestExamples": [],
  "responseExamples": [
    {
      "status": "200",
      "contentType": "application/json",
      "example": "{\"isLast\":true,\"maxResults\":100,\"startAt\":0,\"total\":3,\"values\":[{\"issueTypeScheme\":{\"id\":\"10000\",\"name\":\"Default Issue Type Scheme\",\"description\":\"Default issue type scheme is the list of global issue types. All newly created issue types will automatically be added to this scheme.\",\"defaultIssueTypeId\":\"10003\",\"isDefault\":true},\"projectIds\":[\"10000\",\"10001\"]},{\"issueTypeScheme\":{\"id\":\"10001\",\"name\":\"SUP: Kanban Issue Type Scheme\",\"description\":\"A collection of issue types suited to use in a kanban style project.\"},\"projectIds\":[\"10002\"]},{\"issueTypeScheme\":{\"id\":\"10002\",\"name\":\"HR: Scrum issue type scheme\",\"description\":\"\",\"defaultIssueTypeId\":\"10004\",\"issueTypes\":{\"isLast\":true,\"maxResults\":100,\"startAt\":0,\"total\":1,\"values\":[{\"description\":\"Improvement Issue Type\",\"hierarchyLevel\":-1,\"iconUrl\":\"www.example.com\",\"id\":\"1000L\",\"name\":\"Improvements\",\"subtask\":true}]}},\"projectIds\":[\"10003\",\"10004\",\"10005\"]}]}"
    }
  ]
}