{
  "$schema": "https://json-schema.org/draft/2020-12/schema",
  "$id": "#/components/schemas/pipeline_step_error",
  "title": "pipeline_step_error",
  "allOf": [
    {
      "$ref": "#/components/schemas/object"
    },
    {
      "additionalProperties": true,
      "type": "object",
      "title": "Pipeline Step Error",
      "description": "An error causing a step failure.",
      "properties": {
        "key": {
          "type": "string",
          "description": "The error key."
        },
        "message": {
          "type": "string",
          "description": "The error message."
        }
      }
    }
  ]
}