{
  "$schema": "https://json-schema.org/draft/2020-12/schema",
  "$id": "#/components/schemas/AvailableWorkflowTriggers",
  "title": "AvailableWorkflowTriggers",
  "additionalProperties": false,
  "description": "The trigger rules available.",
  "properties": {
    "availableTypes": {
      "description": "The list of available trigger types.",
      "items": {
        "$ref": "#/components/schemas/AvailableWorkflowTriggerTypes"
      },
      "type": "array"
    },
    "ruleKey": {
      "description": "The rule key of the rule.",
      "type": "string"
    }
  },
  "required": [
    "availableTypes",
    "ruleKey"
  ],
  "type": "object"
}